{"updated":"2026-07-17T14:48:22.551Z","count":22,"tickers":[{"sym":"SPY","spot":746.06,"asof":"2026-07-17T10:32:13","exps":10,"n":3522,"bars":502},{"sym":"QQQ","spot":696.599,"asof":"2026-07-17T10:32:18","exps":10,"n":3476,"bars":502},{"sym":"IWM","spot":295.28,"asof":"2026-07-17T10:32:13","exps":10,"n":1718,"bars":502},{"sym":"DIA","spot":524.56,"asof":"2026-07-17T10:29:44","exps":10,"n":1722,"bars":502},{"sym":"NVDA","spot":203.81,"asof":"2026-07-17T10:32:18","exps":10,"n":780,"bars":502},{"sym":"TSLA","spot":379.57,"asof":"2026-07-17T10:32:21","exps":10,"n":1514,"bars":502},{"sym":"AAPL","spot":333.01,"asof":"2026-07-17T10:32:05","exps":10,"n":976,"bars":502},{"sym":"MSFT","spot":392.61,"asof":"2026-07-17T10:32:11","exps":10,"n":1316,"bars":502},{"sym":"AMZN","spot":248.34,"asof":"2026-07-17T10:32:14","exps":10,"n":868,"bars":502},{"sym":"META","spot":633.8,"asof":"2026-07-17T10:32:04","exps":10,"n":2184,"bars":502},{"sym":"GOOGL","spot":345.2,"asof":"2026-07-17T10:32:17","exps":10,"n":1150,"bars":502},{"sym":"AMD","spot":486.39,"asof":"2026-07-17T10:32:14","exps":10,"n":2096,"bars":502},{"sym":"AVGO","spot":370.66,"asof":"2026-07-17T10:32:18","exps":10,"n":1394,"bars":502},{"sym":"MU","spot":864.63,"asof":"2026-07-17T10:32:21","exps":10,"n":2678,"bars":502},{"sym":"SMCI","spot":24.21,"asof":"2026-07-17T10:32:10","exps":10,"n":414,"bars":502},{"sym":"PLTR","spot":132.21,"asof":"2026-07-17T10:32:15","exps":10,"n":778,"bars":502},{"sym":"COIN","spot":157.93,"asof":"2026-07-17T10:22:13","exps":10,"n":748,"bars":502},{"sym":"MSTR","spot":92.95,"asof":"2026-07-17T10:32:08","exps":10,"n":728,"bars":502},{"sym":"NFLX","spot":67.79,"asof":"2026-07-17T10:32:10","exps":10,"n":598,"bars":502},{"sym":"SPX","spot":7483.52,"asof":"2026-07-17T10:32:56","exps":10,"n":5868,"bars":0},{"sym":"NDX","spot":28593.1641,"asof":"2026-07-17T10:33:07","exps":10,"n":6242,"bars":0},{"sym":"VIX","spot":18.14,"asof":"2026-07-17T10:32:01","exps":10,"n":356,"bars":0}]}